odoo/addons/stock_inventory/README.rst
odoo/addons/stock_inventory/__init__.py
odoo/addons/stock_inventory/__manifest__.py
odoo/addons/stock_inventory/i18n/es.po
odoo/addons/stock_inventory/i18n/fr.po
odoo/addons/stock_inventory/i18n/it.po
odoo/addons/stock_inventory/i18n/stock_inventory.pot
odoo/addons/stock_inventory/i18n/tr.po
odoo/addons/stock_inventory/models/__init__.py
odoo/addons/stock_inventory/models/res_company.py
odoo/addons/stock_inventory/models/res_config_settings.py
odoo/addons/stock_inventory/models/stock_inventory.py
odoo/addons/stock_inventory/models/stock_move_line.py
odoo/addons/stock_inventory/models/stock_quant.py
odoo/addons/stock_inventory/readme/CONTRIBUTORS.md
odoo/addons/stock_inventory/readme/DESCRIPTION.md
odoo/addons/stock_inventory/readme/USAGE.md
odoo/addons/stock_inventory/security/ir.model.access.csv
odoo/addons/stock_inventory/security/security.xml
odoo/addons/stock_inventory/static/description/icon.png
odoo/addons/stock_inventory/static/description/index.html
odoo/addons/stock_inventory/tests/__init__.py
odoo/addons/stock_inventory/tests/test_stock_inventory.py
odoo/addons/stock_inventory/views/res_config_settings_view.xml
odoo/addons/stock_inventory/views/stock_inventory.xml
odoo/addons/stock_inventory/views/stock_move_line.xml
odoo/addons/stock_inventory/views/stock_quant.xml
odoo_addon_stock_inventory-19.0.1.0.0.2.dist-info/METADATA
odoo_addon_stock_inventory-19.0.1.0.0.2.dist-info/WHEEL
odoo_addon_stock_inventory-19.0.1.0.0.2.dist-info/top_level.txt
odoo_addon_stock_inventory-19.0.1.0.0.2.dist-info/RECORD
