Metadata-Version: 2.1
Name: odoo-addon-stock_inventory
Version: 19.0.1.0.0.2
Requires-Dist: odoo==19.0.*
Summary: Allows to do an easier follow up of the Inventory Adjustments
Home-page: https://github.com/OCA/stock-logistics-warehouse
License: LGPL-3
Author: ForgeFlow, Odoo Community Association (OCA)
Author-email: support@odoo-community.org
Classifier: Programming Language :: Python
Classifier: Framework :: Odoo
Classifier: Framework :: Odoo :: 19.0
Classifier: License :: OSI Approved :: GNU Lesser General Public License v3 (LGPLv3)
Classifier: Development Status :: 4 - Beta
